st2smv/Makefile.run
st2smv/__init__.py
st2smv/__main__.py
st2smv/ast.py
st2smv/delay_timer.smv
st2smv/ir.py
st2smv/smv.py
st2smv/st.py
st2smv/utils.py
st2smv/plugins/__init__.py
st2smv/plugins/actions.py
st2smv/plugins/connectivity/__init__.py
st2smv/plugins/connectivity/bfs.py
st2smv/plugins/connectivity/cone_of_influence.py
st2smv/plugins/connectivity/connectivity.py
st2smv/plugins/irrelevant_logic/__init__.py
st2smv/plugins/irrelevant_logic/irrelevant_logic.py
st2smv/plugins/stdlib/__init__.py
st2smv/plugins/stdlib/stdlib.py
st2smv/plugins/varlock/__init__.py
st2smv/plugins/varlock/varlock.py
st2smv-0.1.2.dist-info/DESCRIPTION.rst
st2smv-0.1.2.dist-info/METADATA
st2smv-0.1.2.dist-info/RECORD
st2smv-0.1.2.dist-info/WHEEL
st2smv-0.1.2.dist-info/entry_points.txt
st2smv-0.1.2.dist-info/metadata.json
st2smv-0.1.2.dist-info/top_level.txt
