Metadata-Version: 2.0
Name: st2smv
Version: 0.1.2
Summary: A tool to convert Structured Text PLC code to an SMV model.
Home-page: https://pypi.python.org/pypi/st2smv
Author: Blake C. Rawlings
Author-email: blakecraw@gmail.com
License: GPLv3+
Platform: UNKNOWN
Classifier: Development Status :: 3 - Alpha
Classifier: Intended Audience :: Science/Research
Classifier: License :: OSI Approved :: GNU General Public License v3 or later (GPLv3+)
Classifier: Operating System :: POSIX
Classifier: Programming Language :: Python :: 2
Classifier: Programming Language :: Python :: 3
Classifier: Programming Language :: Python :: Implementation :: CPython
Classifier: Programming Language :: Python :: Implementation :: PyPy
Classifier: Topic :: Scientific/Engineering
Requires-Dist: networkx
Requires-Dist: pyparsing
Requires-Dist: six
